Materials_Data_Analytics/__init__.py
Materials_Data_Analytics/laws_and_constants.py
Materials_Data_Analytics/continuum_modelling/__init__.py
Materials_Data_Analytics/continuum_modelling/microkinetic_modelling.py
Materials_Data_Analytics/core/__init__.py
Materials_Data_Analytics/core/coordinate_transformer.py
Materials_Data_Analytics/core/universe.py
Materials_Data_Analytics/experiment_modelling/__init__.py
Materials_Data_Analytics/experiment_modelling/core.py
Materials_Data_Analytics/experiment_modelling/cyclic_voltammetry.py
Materials_Data_Analytics/experiment_modelling/giwaxs.py
Materials_Data_Analytics/materials/__init__.py
Materials_Data_Analytics/materials/electrolytes.py
Materials_Data_Analytics/materials/ions.py
Materials_Data_Analytics/materials/material_lists.py
Materials_Data_Analytics/materials/polymers.py
Materials_Data_Analytics/materials/solutes.py
Materials_Data_Analytics/materials/solvents.py
Materials_Data_Analytics/metadynamics/__init__.py
Materials_Data_Analytics/metadynamics/free_energy.py
Materials_Data_Analytics/metadynamics/path_analysis.py
Materials_Data_Analytics/quantum_chemistry/__init__.py
Materials_Data_Analytics/quantum_chemistry/gaussian.py
cli_tools/__init__.py
cli_tools/colvar_plotter.py
cli_tools/get_cv_sample.py
cli_tools/get_polymer_contacts.py
cli_tools/plot_hills.py
dash_app/__init__.py
dash_app/app.py
dash_app/pages/CyclicVoltammogram.py
dash_app/pages/__init__.py
dash_app/pages/home.py
materials_data_analytics-6.2.9.data/scripts/colvar_plotter.py
materials_data_analytics-6.2.9.data/scripts/get_cv_sample.py
materials_data_analytics-6.2.9.data/scripts/get_polymer_contacts.py
materials_data_analytics-6.2.9.data/scripts/plot_hills.py
test/__init__.py
test/test_coordinate_transformer.py
test/test_cyclic_voltammetry.py
test/test_free_energy.py
test/test_gaussian.py
test/test_giwaxs.py
test/test_materials.py
test/test_microkinetic_model.py
test/test_path.py
test/test_universe.py
materials_data_analytics-6.2.9.dist-info/LICENCE.txt
materials_data_analytics-6.2.9.dist-info/METADATA
materials_data_analytics-6.2.9.dist-info/WHEEL
materials_data_analytics-6.2.9.dist-info/entry_points.txt
materials_data_analytics-6.2.9.dist-info/top_level.txt
materials_data_analytics-6.2.9.dist-info/RECORD
