Metadata-Version: 2.2
Name: Materials_Data_Analytics
Version: 6.2.9
Summary: Data analysis package for materials characterisation at Stanford University
Home-page: https://github.com/nicholas9182/Materials_Data_Analytics/
Author: Material Science Stanford
Author-email: nsiemons@stanford.edu
Classifier: Programming Language :: Python :: 3
Classifier: License :: OSI Approved :: MIT License
Classifier: Operating System :: OS Independent
Requires-Python: >=3.10
License-File: LICENCE.txt
Requires-Dist: scipy
Requires-Dist: pandas
Requires-Dist: plotly
Requires-Dist: matplotlib
Requires-Dist: typer
Requires-Dist: click
Requires-Dist: numpy
Requires-Dist: networkx
Requires-Dist: MDAnalysis
Requires-Dist: dash
Requires-Dist: kaleido
Requires-Dist: Datetime
Requires-Dist: lmfit
Dynamic: author
Dynamic: author-email
Dynamic: classifier
Dynamic: home-page
Dynamic: requires-dist
Dynamic: requires-python
Dynamic: summary
